minimal_python_project_skeleton/__init__.py
minimal_python_project_skeleton-0.2.1.dist-info/LICENSE
minimal_python_project_skeleton-0.2.1.dist-info/METADATA
minimal_python_project_skeleton-0.2.1.dist-info/WHEEL
minimal_python_project_skeleton-0.2.1.dist-info/top_level.txt
minimal_python_project_skeleton-0.2.1.dist-info/RECORD
