Metadata-Version: 2.1
Name: minimal_python_project_skeleton
Version: 0.2.1
License: MIT
Project-URL: Changelog, https://github.com/MArpogaus/minimal_python_project_skeleton/blob/dev/CHANGELOG.md
Project-URL: Documentation, https://marpogaus.github.io/minimal_python_project_skeleton
Project-URL: Issues, https://github.com/MArpogaus/minimal_python_project_skeleton/issues
Project-URL: Repository, https://github.com/MArpogaus/minimal_python_project_skeleton
Classifier: Programming Language :: Python :: 3.7
Classifier: Programming Language :: Python :: 3.8
Classifier: Programming Language :: Python :: 3.9
Classifier: Programming Language :: Python :: 3.10
Classifier: Programming Language :: Python :: 3.11
Requires-Python: <3.12,>=3.7
License-File: LICENSE
Provides-Extra: develop
Requires-Dist: minimal-python-project-skeleton[test] ; extra == 'develop'
Requires-Dist: commitizen ; extra == 'develop'
Requires-Dist: ipykernel ; extra == 'develop'
Requires-Dist: pre-commit ; extra == 'develop'
Requires-Dist: pylsp-rope ; extra == 'develop'
Requires-Dist: python-lsp-ruff ; extra == 'develop'
Requires-Dist: python-lsp-server[all] ; extra == 'develop'
Requires-Dist: ruff ; extra == 'develop'
Provides-Extra: docs
Requires-Dist: pdoc ; extra == 'docs'
Provides-Extra: test
Requires-Dist: pytest ; extra == 'test'
Requires-Dist: pytest-xdist ; extra == 'test'
